[
    {
        "title": "絵空随筆神域",
        "subtitle": "Esora Somesaki Blog Collection",
        "domain": "blog",
        "albumTitle": "幻想界域伝説",
        "albumSubtitle": "Fairy Fantasy from TarikkoChan the Messenger",
        "number": "１"
    },
    {
        "title": "秘封共享庫",
        "subtitle": "Selfish Pseudo Repository of Commons",
        "domain": "commons",
        "albumTitle": "幻想界域伝説",
        "albumSubtitle": "Fairy Fantasy from TarikkoChan the Messenger",
        "number": "２"
    },
    {
        "title": "幽冥封卷则",
        "subtitle": "Assigned Motivation from Publicly Owned Conference",
        "domain": "dollopium",
        "albumTitle": "幻想界域伝説",
        "albumSubtitle": "Fairy Fantasy from TarikkoChan the Messenger",
        "number": "３"
    },
    {
        "title": "幻想界域巡録",
        "subtitle": "TarikkoChan's Second Level Domain Index",
        "domain": "index",
        "albumTitle": "幻想界域伝説",
        "albumSubtitle": "Fairy Fantasy from TarikkoChan the Messenger",
        "number": "４"
    },
    {
        "title": "鏡映幻夢殿",
        "subtitle": "Mapped Reflection Treasury",
        "domain": "mirrors.sdick",
        "albumTitle": "幻想界域伝説",
        "albumSubtitle": "Fairy Fantasy from TarikkoChan the Messenger",
        "number": "５"
    },
    {
        "title": "笛客樂団の歷史",
        "subtitle": "History of the Dick",
        "domain": "sdick-old",
        "albumTitle": "大空笛客",
        "albumSubtitle": "Dickal Astronomy",
        "number": "１４"
    },
    {
        "title": "秘封創培幻想名録",
        "subtitle": "128 Victims' Scattered Fair Directory",
        "domain": "sdick",
        "albumTitle": "創培部奇譚",
        "albumSubtitle": "Horrible Story of Shikō Chūgaku Sōbai-Bu",
        "number": "３"
    },
    {
        "title": "黑色牛像",
        "subtitle": "Mascot of Sōbai-Bu",
        "domain": "sdickd-1",
        "albumTitle": "創培部奇譚",
        "albumSubtitle": "Horrible Story of Shikō Chūgaku Sōbai-Bu",
        "number": "６"
    },
    {
        "title": "灯花的三件事",
        "subtitle": "Ri Takeshi's 3 Things",
        "domain": "sdickd-2",
        "albumTitle": "創培部奇譚",
        "albumSubtitle": "Horrible Story of Shikō Chūgaku Sōbai-Bu",
        "number": "８"
    },
    {
        "title": "屈指可數的日子",
        "subtitle": "Finger-Countable Days",
        "domain": "sdickd",
        "albumTitle": "創培部奇譚",
        "albumSubtitle": "Horrible Story of Shikō Chūgaku Sōbai-Bu",
        "number": "９"
    },
    {
        "title": "輪迴回環結界",
        "subtitle": "Reincarnation Loop of the Directory",
        "domain": "www",
        "albumTitle": "幻想界域伝説",
        "albumSubtitle": "Fairy Fantasy from TarikkoChan the Messenger",
        "number": "６"
    },
    {
        "title": "地下創世記",
        "subtitle": "Ionic Fish's Mine & Craft Carnival Server",
        "domain": "play",
        "albumTitle": "幻想界域伝説",
        "albumSubtitle": "Fairy Fantasy from TarikkoChan the Messenger",
        "number": "７"
    }
]